kumaoche/__init__.py
kumaoche/container.py
kumaoche/config/__init__.py
kumaoche/config/config_pack.py
kumaoche/config/config_parser.py
kumaoche/config/exec_env/__init__.py
kumaoche/config/exec_env/docker_config.py
kumaoche/config/exec_env/exec_env_config.py
kumaoche/config/exec_env/shell_config.py
kumaoche/config/exec_env/string_builder_config.py
kumaoche/config/service/__init__.py
kumaoche/config/service/db_config.py
kumaoche/config/service/git_config.py
kumaoche/config/service/package_service_config.py
kumaoche/config/service/service_config.py
kumaoche/exec_env/__init__.py
kumaoche/exec_env/disable.py
kumaoche/exec_env/docker.py
kumaoche/exec_env/exec_env.py
kumaoche/exec_env/shell.py
kumaoche/exec_env/string_builder.py
kumaoche/runner/__init__.py
kumaoche/runner/invoke_runner.py
kumaoche/runner/runner.py
kumaoche/service/__init__.py
kumaoche/service/db.py
kumaoche/service/git.py
kumaoche/service/package_manager.py
kumaoche/service/service.py
tests/config/__init__.py
tests/config/stub_config.py
tests/config/test_config_pack.py
tests/config/test_config_parser.py
tests/config/exec_env/__init__.py
tests/config/exec_env/test_docker_config.py
tests/config/exec_env/test_shell_config.py
tests/config/exec_env/test_string_builder_config.py
tests/config/service/__init__.py
tests/config/service/test_db_config.py
tests/config/service/test_git_config.py
tests/config/service/test_package_manager_config.py
tests/exec_env/__init__.py
tests/exec_env/moc_env.py
tests/exec_env/test_disable.py
tests/exec_env/test_docker.py
tests/exec_env/test_shell.py
tests/runner/__init__.py
tests/runner/moc_runner.py
tests/service/__init__.py
tests/service/test_db.py
tests/service/test_git.py
tests/service/test_package_manager.py
kumaoche-0.1.24.dist-info/LICENSE
kumaoche-0.1.24.dist-info/METADATA
kumaoche-0.1.24.dist-info/WHEEL
kumaoche-0.1.24.dist-info/top_level.txt
kumaoche-0.1.24.dist-info/RECORD
