Metadata-Version: 2.1
Name: kumaoche
Version: 0.1.24
Summary: Pythonic Dev Repository & Dev Environment Management tool.
Home-page: https://github.com/kumak1/kumaoche
Author: kumak1
Author-email: kumaki0@gmail.com
License: MIT License
Requires-Dist: invoke
Requires-Dist: pyyaml
